{"school":"장영실고","events":[
{"start":"2026-03-02","end":"2026-03-02","title":"대체 휴무일","category":"공휴일"},
{"start":"2026-03-03","end":"2026-03-03","title":"입학식, 개학식","category":"행사"},
{"start":"2026-03-09","end":"2026-03-09","title":"1,2학년 기초학력 진단평가","category":"기타"},
{"start":"2026-03-11","end":"2026-03-11","title":"1학기 학급정부반장 선거","category":"행사"},
{"start":"2026-03-16","end":"2026-03-27","title":"가정방문 및 상담주간","category":"행사"},
{"start":"2026-03-18","end":"2026-03-18","title":"민방위 훈련","category":"기타"},
{"start":"2026-03-31","end":"2026-03-31","title":"학교 교육과정 설명회","category":"행사"},
{"start":"2026-04-10","end":"2026-04-11","title":"학생회 워크숍","category":"행사"},
{"start":"2026-04-23","end":"2026-04-24","title":"1학기 1회시험","category":"시험"},
{"start":"2026-04-29","end":"2026-05-01","title":"1학년 수련활동","category":"행사"},
{"start":"2026-05-04","end":"2026-05-04","title":"학교장 재량휴업일","category":"휴업"},
{"start":"2026-05-05","end":"2026-05-05","title":"어린이날(수업교체 월↔목)","category":"공휴일"},
{"start":"2026-05-13","end":"2026-05-13","title":"민방위 훈련","category":"기타"},
{"start":"2026-05-21","end":"2026-05-21","title":"수업 공개의 날","category":"행사"},
{"start":"2026-05-25","end":"2026-05-25","title":"석가탄신일 대체 휴무일","category":"공휴일"},
{"start":"2026-05-30","end":"2026-05-30","title":"학교 방문의 날","category":"행사"},
{"start":"2026-06-03","end":"2026-06-03","title":"지방선거","category":"공휴일"},
{"start":"2026-06-22","end":"2026-06-24","title":"1학기 2회시험","category":"시험"},
{"start":"2026-07-16","end":"2026-07-16","title":"방학식","category":"방학"},
{"start":"2026-07-17","end":"2026-07-17","title":"제헌절","category":"공휴일"},
{"start":"2026-08-18","end":"2026-08-18","title":"개학식","category":"행사"},
{"start":"2026-08-20","end":"2026-08-20","title":"민방위 훈련","category":"기타"},
{"start":"2026-08-26","end":"2026-08-26","title":"2학기 학급정부반장 선거","category":"행사"},
{"start":"2026-08-24","end":"2026-09-04","title":"가정방문 및 상담주간","category":"행사"},
{"start":"2026-09-18","end":"2026-09-18","title":"춘계 체육대회","category":"행사"},
{"start":"2026-09-19","end":"2026-09-19","title":"학교 방문의 날","category":"행사"},
{"start":"2026-09-24","end":"2026-09-25","title":"추석연휴(수업교체 목↔월)","category":"공휴일"},
{"start":"2026-10-01","end":"2026-10-02","title":"2학기 1회시험","category":"시험"},
{"start":"2026-10-05","end":"2026-10-05","title":"개천절 대체 휴무일","category":"공휴일"},
{"start":"2026-10-09","end":"2026-10-09","title":"한글날","category":"공휴일"},
{"start":"2026-10-21","end":"2026-10-23","title":"2학년 수학여행","category":"행사"},
{"start":"2026-10-23","end":"2026-10-23","title":"1,3학년 현장체험학습","category":"행사"},
{"start":"2026-11-04","end":"2026-11-04","title":"민방위 훈련","category":"기타"},
{"start":"2026-11-19","end":"2026-11-19","title":"재량휴업일-대입수능","category":"휴업"},
{"start":"2026-11-20","end":"2026-11-20","title":"학교장 재량휴업일(수업교체 금↔화)","category":"휴업"},
{"start":"2026-12-02","end":"2026-12-04","title":"2학기 2회시험","category":"시험"},
{"start":"2026-12-25","end":"2026-12-25","title":"성탄절","category":"공휴일"},
{"start":"2027-01-01","end":"2027-01-01","title":"설날","category":"공휴일"},
{"start":"2027-01-08","end":"2027-01-08","title":"종업식, 졸업식","category":"행사"}
]}
